ChromeKuozhanJiYingyongKaifaShoufaBan/README.md
ChromeKuozhanJiYingyongKaifaShoufaBan/__init__.py
ChromeKuozhanJiYingyongKaifaShoufaBan/__main__.py
ChromeKuozhanJiYingyongKaifaShoufaBan/file.epub
ChromeKuozhanJiYingyongKaifaShoufaBan/index.html
ChromeKuozhanJiYingyongKaifaShoufaBan/css/__init__.py
ChromeKuozhanJiYingyongKaifaShoufaBan/css/annotations.css
ChromeKuozhanJiYingyongKaifaShoufaBan/css/main.css
ChromeKuozhanJiYingyongKaifaShoufaBan/css/normalize.css
ChromeKuozhanJiYingyongKaifaShoufaBan/css/popup.css
ChromeKuozhanJiYingyongKaifaShoufaBan/font/__init__.py
ChromeKuozhanJiYingyongKaifaShoufaBan/font/fontello.eot
ChromeKuozhanJiYingyongKaifaShoufaBan/font/fontello.svg
ChromeKuozhanJiYingyongKaifaShoufaBan/font/fontello.ttf
ChromeKuozhanJiYingyongKaifaShoufaBan/font/fontello.woff
ChromeKuozhanJiYingyongKaifaShoufaBan/img/__init__.py
ChromeKuozhanJiYingyongKaifaShoufaBan/img/annotator-glyph-sprite.png
ChromeKuozhanJiYingyongKaifaShoufaBan/img/annotator-icon-sprite.png
ChromeKuozhanJiYingyongKaifaShoufaBan/img/apple-touch-icon.png
ChromeKuozhanJiYingyongKaifaShoufaBan/img/cancelfullscreen.png
ChromeKuozhanJiYingyongKaifaShoufaBan/img/close.png
ChromeKuozhanJiYingyongKaifaShoufaBan/img/fullscreen.png
ChromeKuozhanJiYingyongKaifaShoufaBan/img/loader.gif
ChromeKuozhanJiYingyongKaifaShoufaBan/img/menu-icon.png
ChromeKuozhanJiYingyongKaifaShoufaBan/img/save.png
ChromeKuozhanJiYingyongKaifaShoufaBan/img/saved.png
ChromeKuozhanJiYingyongKaifaShoufaBan/img/settings-s.png
ChromeKuozhanJiYingyongKaifaShoufaBan/img/settings.png
ChromeKuozhanJiYingyongKaifaShoufaBan/img/star.png
ChromeKuozhanJiYingyongKaifaShoufaBan/js/__init__.py
ChromeKuozhanJiYingyongKaifaShoufaBan/js/epub.js
ChromeKuozhanJiYingyongKaifaShoufaBan/js/epub.min.js
ChromeKuozhanJiYingyongKaifaShoufaBan/js/epub.min.map
ChromeKuozhanJiYingyongKaifaShoufaBan/js/hooks.min.js
ChromeKuozhanJiYingyongKaifaShoufaBan/js/hooks.min.map
ChromeKuozhanJiYingyongKaifaShoufaBan/js/reader.js
chrome_kuozhan_ji_yingyong_kaifa_shoufa_ban-2024.3.1.0.dist-info/METADATA
chrome_kuozhan_ji_yingyong_kaifa_shoufa_ban-2024.3.1.0.dist-info/WHEEL
chrome_kuozhan_ji_yingyong_kaifa_shoufa_ban-2024.3.1.0.dist-info/entry_points.txt
chrome_kuozhan_ji_yingyong_kaifa_shoufa_ban-2024.3.1.0.dist-info/top_level.txt
chrome_kuozhan_ji_yingyong_kaifa_shoufa_ban-2024.3.1.0.dist-info/RECORD
